README.md
jw
setup.py
bio/__init__.py
bio/config.ini
bio/config.py
bio/handler.py
bio/snippet.py
bio/cli/__init__.py
bio/cli/gfunc.py
bio/cli/parser.py
bio/cli/sqlfunc.py
bio/scripts/cpq.sh
bio/scripts/ed.sh
bio/templates/docstring.sql
bio/templates/posting.md
bio/templates/problem.md
cal/__init__.py
cal/__main__.py
cal/console_calendar.py
cal/example.py
cal/googleoauth.py
cal/inputconfig.py
cal/string_cleanup.py
cal/util.py
imgcat/__init__.py
imgcat/__main__.py
imgcat/img.py
jira/__init__.py
jira/confluence_api.py
jira/crawl_doc.py
jira/jira_api.py
jw.egg-info/PKG-INFO
jw.egg-info/SOURCES.txt
jw.egg-info/dependency_links.txt
jw.egg-info/requires.txt
jw.egg-info/top_level.txt
md2ppt/__init__.py
md2ppt/__main__.py
md2ppt/feature.py
md2ppt/util/__init__.py
md2ppt/util/getch.py
util/__init__.py
util/key_event.py
util/profiling.py
util/property.py
util/sql_core.py
util/sql_model.py
util/sql_tag.py
util/ui.py