Metadata-Version: 2.1
Name: jw
Version: 1.0
Summary: I just want to search and write my notesregardless of their file name ...
Home-page: https://github.com/jongwony/jw
Author: jongwony
Author-email: lastone9182@gmail.com
License: UNKNOWN
Platform: UNKNOWN
Provides-Extra: crawl
